Metadata-Version: 2.1
Name: trendyol-api-python-sdk
Version: 0.0.8
Summary: Unofficial Trendyol API Python Client
Home-page: https://github.com/altuntasmuhammet/trendyol-api-python-sdk
Author: Muhammed Ali Altuntas
Author-email: altuntasmuhammet96@gmail.com
License: MIT
Classifier: Programming Language :: Python :: 3
Classifier: License :: OSI Approved :: MIT License
Classifier: Operating System :: OS Independent
Requires-Python: >=3.0
License-File: LICENSE
Requires-Dist: requests
